google_cloud_logger/__init__.py
test/__init__.py
test/google_cloud_logger/__init__.py
test/google_cloud_logger/conftest.py
test/google_cloud_logger/test_google_cloud_formatter.py
google_cloud_logger-0.2.1.dist-info/LICENSE
google_cloud_logger-0.2.1.dist-info/METADATA
google_cloud_logger-0.2.1.dist-info/WHEEL
google_cloud_logger-0.2.1.dist-info/top_level.txt
google_cloud_logger-0.2.1.dist-info/RECORD
