Metadata-Version: 2.1
Name: google-cloud-logger
Version: 0.2.1
Summary: Google Cloud Logger Formatter
Home-page: http://github.com/rai200890/python_google_cloud_logger
Author: Raissa Ferreira
Author-email: rai200890@gmail.com
License: MIT
Platform: UNKNOWN
Classifier: Environment :: Web Environment
Classifier: Intended Audience :: Developers
Classifier: License :: OSI Approved :: MIT License
Classifier: Natural Language :: English
Classifier: Operating System :: OS Independent
Classifier: Programming Language :: Python :: 3 :: Only
Classifier: Topic :: System :: Logging
Requires-Python: >=3.4.*
Requires-Dist: python-json-logger (>=0.1.10)
